[
  {
    "id": 1,
    "lat": 33.6595,
    "lng": -117.9988,
    "info": "Huntington Beach",
    "wiki": "Huntington_Beach,_California",
    "data": {
      "status": 200,
      "callCount": 1,
      "copyright": "Tidal data retrieved from www.worldtides.info. Copyright (c) 2014-2021 Brainware LLC. Licensed for use of individual spatial coordinates on behalf of/by an end-user. Source data created by the Center for Operational Oceanographic Products and Services (CO-OPS) and is not subject to copyright protection. NO GUARANTEES ARE MADE ABOUT THE CORRECTNESS OF THIS DATA. You may not use it if anyone or anything could come to harm as a result of using it (e.g. for navigational purposes).",
      "requestLat": 33.6595,
      "requestLon": -117.9988,
      "responseLat": 33.63,
      "responseLon": -117.958,
      "atlas": "NOAA",
      "station": "Santa Ana River entrance (inside), California",
      "heights": [
        {
          "dt": 1733236200,
          "date": "2024-12-03T14:30+0000",
          "height": -0.017
        },
        {
          "dt": 1733238000,
          "date": "2024-12-03T15:00+0000",
          "height": 0.064
        },
        {
          "dt": 1733239800,
          "date": "2024-12-03T15:30+0000",
          "height": 0.153
        },
        {
          "dt": 1733241600,
          "date": "2024-12-03T16:00+0000",
          "height": 0.243
        },
        {
          "dt": 1733243400,
          "date": "2024-12-03T16:30+0000",
          "height": 0.331
        },
        {
          "dt": 1733245200,
          "date": "2024-12-03T17:00+0000",
          "height": 0.411
        },
        {
          "dt": 1733247000,
          "date": "2024-12-03T17:30+0000",
          "height": 0.478
        },
        {
          "dt": 1733248800,
          "date": "2024-12-03T18:00+0000",
          "height": 0.527
        },
        {
          "dt": 1733250600,
          "date": "2024-12-03T18:30+0000",
          "height": 0.554
        },
        {
          "dt": 1733252400,
          "date": "2024-12-03T19:00+0000",
          "height": 0.558
        },
        {
          "dt": 1733254200,
          "date": "2024-12-03T19:30+0000",
          "height": 0.538
        },
        {
          "dt": 1733256000,
          "date": "2024-12-03T20:00+0000",
          "height": 0.493
        },
        {
          "dt": 1733257800,
          "date": "2024-12-03T20:30+0000",
          "height": 0.427
        },
        {
          "dt": 1733259600,
          "date": "2024-12-03T21:00+0000",
          "height": 0.341
        },
        {
          "dt": 1733261400,
          "date": "2024-12-03T21:30+0000",
          "height": 0.24
        },
        {
          "dt": 1733263200,
          "date": "2024-12-03T22:00+0000",
          "height": 0.13
        },
        {
          "dt": 1733265000,
          "date": "2024-12-03T22:30+0000",
          "height": 0.017
        },
        {
          "dt": 1733266800,
          "date": "2024-12-03T23:00+0000",
          "height": -0.095
        },
        {
          "dt": 1733268600,
          "date": "2024-12-03T23:30+0000",
          "height": -0.198
        },
        {
          "dt": 1733270400,
          "date": "2024-12-04T00:00+0000",
          "height": -0.289
        },
        {
          "dt": 1733272200,
          "date": "2024-12-04T00:30+0000",
          "height": -0.362
        },
        {
          "dt": 1733274000,
          "date": "2024-12-04T01:00+0000",
          "height": -0.414
        },
        {
          "dt": 1733275800,
          "date": "2024-12-04T01:30+0000",
          "height": -0.445
        },
        {
          "dt": 1733277600,
          "date": "2024-12-04T02:00+0000",
          "height": -0.452
        },
        {
          "dt": 1733279400,
          "date": "2024-12-04T02:30+0000",
          "height": -0.438
        },
        {
          "dt": 1733281200,
          "date": "2024-12-04T03:00+0000",
          "height": -0.404
        },
        {
          "dt": 1733283000,
          "date": "2024-12-04T03:30+0000",
          "height": -0.354
        },
        {
          "dt": 1733284800,
          "date": "2024-12-04T04:00+0000",
          "height": -0.292
        },
        {
          "dt": 1733286600,
          "date": "2024-12-04T04:30+0000",
          "height": -0.222
        },
        {
          "dt": 1733288400,
          "date": "2024-12-04T05:00+0000",
          "height": -0.15
        },
        {
          "dt": 1733290200,
          "date": "2024-12-04T05:30+0000",
          "height": -0.081
        },
        {
          "dt": 1733292000,
          "date": "2024-12-04T06:00+0000",
          "height": -0.018
        },
        {
          "dt": 1733293800,
          "date": "2024-12-04T06:30+0000",
          "height": 0.035
        },
        {
          "dt": 1733295600,
          "date": "2024-12-04T07:00+0000",
          "height": 0.074
        },
        {
          "dt": 1733297400,
          "date": "2024-12-04T07:30+0000",
          "height": 0.098
        },
        {
          "dt": 1733299200,
          "date": "2024-12-04T08:00+0000",
          "height": 0.106
        },
        {
          "dt": 1733301000,
          "date": "2024-12-04T08:30+0000",
          "height": 0.099
        },
        {
          "dt": 1733302800,
          "date": "2024-12-04T09:00+0000",
          "height": 0.078
        },
        {
          "dt": 1733304600,
          "date": "2024-12-04T09:30+0000",
          "height": 0.046
        },
        {
          "dt": 1733306400,
          "date": "2024-12-04T10:00+0000",
          "height": 0.006
        },
        {
          "dt": 1733308200,
          "date": "2024-12-04T10:30+0000",
          "height": -0.038
        },
        {
          "dt": 1733310000,
          "date": "2024-12-04T11:00+0000",
          "height": -0.082
        },
        {
          "dt": 1733311800,
          "date": "2024-12-04T11:30+0000",
          "height": -0.123
        },
        {
          "dt": 1733313600,
          "date": "2024-12-04T12:00+0000",
          "height": -0.155
        },
        {
          "dt": 1733315400,
          "date": "2024-12-04T12:30+0000",
          "height": -0.176
        },
        {
          "dt": 1733317200,
          "date": "2024-12-04T13:00+0000",
          "height": -0.183
        },
        {
          "dt": 1733319000,
          "date": "2024-12-04T13:30+0000",
          "height": -0.174
        },
        {
          "dt": 1733320800,
          "date": "2024-12-04T14:00+0000",
          "height": -0.148
        },
        {
          "dt": 1733322600,
          "date": "2024-12-04T14:30+0000",
          "height": -0.106
        },
        {
          "dt": 1733324400,
          "date": "2024-12-04T15:00+0000",
          "height": -0.049
        },
        {
          "dt": 1733326200,
          "date": "2024-12-04T15:30+0000",
          "height": 0.021
        },
        {
          "dt": 1733328000,
          "date": "2024-12-04T16:00+0000",
          "height": 0.1
        },
        {
          "dt": 1733329800,
          "date": "2024-12-04T16:30+0000",
          "height": 0.184
        },
        {
          "dt": 1733331600,
          "date": "2024-12-04T17:00+0000",
          "height": 0.267
        },
        {
          "dt": 1733333400,
          "date": "2024-12-04T17:30+0000",
          "height": 0.346
        },
        {
          "dt": 1733335200,
          "date": "2024-12-04T18:00+0000",
          "height": 0.416
        },
        {
          "dt": 1733337000,
          "date": "2024-12-04T18:30+0000",
          "height": 0.47
        },
        {
          "dt": 1733338800,
          "date": "2024-12-04T19:00+0000",
          "height": 0.507
        },
        {
          "dt": 1733340600,
          "date": "2024-12-04T19:30+0000",
          "height": 0.523
        },
        {
          "dt": 1733342400,
          "date": "2024-12-04T20:00+0000",
          "height": 0.517
        },
        {
          "dt": 1733344200,
          "date": "2024-12-04T20:30+0000",
          "height": 0.487
        },
        {
          "dt": 1733346000,
          "date": "2024-12-04T21:00+0000",
          "height": 0.436
        },
        {
          "dt": 1733347800,
          "date": "2024-12-04T21:30+0000",
          "height": 0.365
        },
        {
          "dt": 1733349600,
          "date": "2024-12-04T22:00+0000",
          "height": 0.278
        },
        {
          "dt": 1733351400,
          "date": "2024-12-04T22:30+0000",
          "height": 0.179
        },
        {
          "dt": 1733353200,
          "date": "2024-12-04T23:00+0000",
          "height": 0.073
        },
        {
          "dt": 1733355000,
          "date": "2024-12-04T23:30+0000",
          "height": -0.034
        },
        {
          "dt": 1733356800,
          "date": "2024-12-05T00:00+0000",
          "height": -0.136
        },
        {
          "dt": 1733358600,
          "date": "2024-12-05T00:30+0000",
          "height": -0.229
        },
        {
          "dt": 1733360400,
          "date": "2024-12-05T01:00+0000",
          "height": -0.308
        },
        {
          "dt": 1733362200,
          "date": "2024-12-05T01:30+0000",
          "height": -0.369
        },
        {
          "dt": 1733364000,
          "date": "2024-12-05T02:00+0000",
          "height": -0.411
        },
        {
          "dt": 1733365800,
          "date": "2024-12-05T02:30+0000",
          "height": -0.43
        },
        {
          "dt": 1733367600,
          "date": "2024-12-05T03:00+0000",
          "height": -0.429
        },
        {
          "dt": 1733369400,
          "date": "2024-12-05T03:30+0000",
          "height": -0.408
        },
        {
          "dt": 1733371200,
          "date": "2024-12-05T04:00+0000",
          "height": -0.369
        },
        {
          "dt": 1733373000,
          "date": "2024-12-05T04:30+0000",
          "height": -0.316
        },
        {
          "dt": 1733374800,
          "date": "2024-12-05T05:00+0000",
          "height": -0.254
        },
        {
          "dt": 1733376600,
          "date": "2024-12-05T05:30+0000",
          "height": -0.186
        },
        {
          "dt": 1733378400,
          "date": "2024-12-05T06:00+0000",
          "height": -0.117
        },
        {
          "dt": 1733380200,
          "date": "2024-12-05T06:30+0000",
          "height": -0.051
        },
        {
          "dt": 1733382000,
          "date": "2024-12-05T07:00+0000",
          "height": 0.007
        },
        {
          "dt": 1733383800,
          "date": "2024-12-05T07:30+0000",
          "height": 0.054
        },
        {
          "dt": 1733385600,
          "date": "2024-12-05T08:00+0000",
          "height": 0.088
        },
        {
          "dt": 1733387400,
          "date": "2024-12-05T08:30+0000",
          "height": 0.108
        },
        {
          "dt": 1733389200,
          "date": "2024-12-05T09:00+0000",
          "height": 0.113
        },
        {
          "dt": 1733391000,
          "date": "2024-12-05T09:30+0000",
          "height": 0.104
        },
        {
          "dt": 1733392800,
          "date": "2024-12-05T10:00+0000",
          "height": 0.082
        },
        {
          "dt": 1733394600,
          "date": "2024-12-05T10:30+0000",
          "height": 0.05
        },
        {
          "dt": 1733396400,
          "date": "2024-12-05T11:00+0000",
          "height": 0.012
        },
        {
          "dt": 1733398200,
          "date": "2024-12-05T11:30+0000",
          "height": -0.03
        },
        {
          "dt": 1733400000,
          "date": "2024-12-05T12:00+0000",
          "height": -0.071
        },
        {
          "dt": 1733401800,
          "date": "2024-12-05T12:30+0000",
          "height": -0.108
        },
        {
          "dt": 1733403600,
          "date": "2024-12-05T13:00+0000",
          "height": -0.137
        },
        {
          "dt": 1733405400,
          "date": "2024-12-05T13:30+0000",
          "height": -0.156
        },
        {
          "dt": 1733407200,
          "date": "2024-12-05T14:00+0000",
          "height": -0.161
        },
        {
          "dt": 1733409000,
          "date": "2024-12-05T14:30+0000",
          "height": -0.151
        }
      ]
    }
  },
  {
    "id": 2,
    "lat": 34.0194,
    "lng": -118.4912,
    "info": "Santa Monica Beach",
    "wiki": "Santa_Monica,_California",
    "data": {
      "status": 200,
      "callCount": 1,
      "copyright": "Tidal data retrieved from www.worldtides.info. Copyright (c) 2014-2021 Brainware LLC. Licensed for use of individual spatial coordinates on behalf of/by an end-user. Source data created by the Center for Operational Oceanographic Products and Services (CO-OPS) and is not subject to copyright protection. NO GUARANTEES ARE MADE ABOUT THE CORRECTNESS OF THIS DATA. You may not use it if anyone or anything could come to harm as a result of using it (e.g. for navigational purposes).",
      "requestLat": 34.0194,
      "requestLon": -118.4912,
      "responseLat": 34.0083,
      "responseLon": -118.5,
      "atlas": "NOAA",
      "station": "Santa Monica, Municipal Pier, San Pedro Channel, California",
      "heights": [
        {
          "dt": 1733236200,
          "date": "2024-12-03T14:30+0000",
          "height": 0.523
        },
        {
          "dt": 1733238000,
          "date": "2024-12-03T15:00+0000",
          "height": 0.649
        },
        {
          "dt": 1733239800,
          "date": "2024-12-03T15:30+0000",
          "height": 0.767
        },
        {
          "dt": 1733241600,
          "date": "2024-12-03T16:00+0000",
          "height": 0.868
        },
        {
          "dt": 1733243400,
          "date": "2024-12-03T16:30+0000",
          "height": 0.944
        },
        {
          "dt": 1733245200,
          "date": "2024-12-03T17:00+0000",
          "height": 0.99
        },
        {
          "dt": 1733247000,
          "date": "2024-12-03T17:30+0000",
          "height": 0.999
        },
        {
          "dt": 1733248800,
          "date": "2024-12-03T18:00+0000",
          "height": 0.97
        },
        {
          "dt": 1733250600,
          "date": "2024-12-03T18:30+0000",
          "height": 0.901
        },
        {
          "dt": 1733252400,
          "date": "2024-12-03T19:00+0000",
          "height": 0.794
        },
        {
          "dt": 1733254200,
          "date": "2024-12-03T19:30+0000",
          "height": 0.652
        },
        {
          "dt": 1733256000,
          "date": "2024-12-03T20:00+0000",
          "height": 0.481
        },
        {
          "dt": 1733257800,
          "date": "2024-12-03T20:30+0000",
          "height": 0.288
        },
        {
          "dt": 1733259600,
          "date": "2024-12-03T21:00+0000",
          "height": 0.082
        },
        {
          "dt": 1733261400,
          "date": "2024-12-03T21:30+0000",
          "height": -0.129
        },
        {
          "dt": 1733263200,
          "date": "2024-12-03T22:00+0000",
          "height": -0.335
        },
        {
          "dt": 1733265000,
          "date": "2024-12-03T22:30+0000",
          "height": -0.528
        },
        {
          "dt": 1733266800,
          "date": "2024-12-03T23:00+0000",
          "height": -0.698
        },
        {
          "dt": 1733268600,
          "date": "2024-12-03T23:30+0000",
          "height": -0.84
        },
        {
          "dt": 1733270400,
          "date": "2024-12-04T00:00+0000",
          "height": -0.946
        },
        {
          "dt": 1733272200,
          "date": "2024-12-04T00:30+0000",
          "height": -1.014
        },
        {
          "dt": 1733274000,
          "date": "2024-12-04T01:00+0000",
          "height": -1.041
        },
        {
          "dt": 1733275800,
          "date": "2024-12-04T01:30+0000",
          "height": -1.029
        },
        {
          "dt": 1733277600,
          "date": "2024-12-04T02:00+0000",
          "height": -0.979
        },
        {
          "dt": 1733279400,
          "date": "2024-12-04T02:30+0000",
          "height": -0.896
        },
        {
          "dt": 1733281200,
          "date": "2024-12-04T03:00+0000",
          "height": -0.788
        },
        {
          "dt": 1733283000,
          "date": "2024-12-04T03:30+0000",
          "height": -0.66
        },
        {
          "dt": 1733284800,
          "date": "2024-12-04T04:00+0000",
          "height": -0.521
        },
        {
          "dt": 1733286600,
          "date": "2024-12-04T04:30+0000",
          "height": -0.38
        },
        {
          "dt": 1733288400,
          "date": "2024-12-04T05:00+0000",
          "height": -0.244
        },
        {
          "dt": 1733290200,
          "date": "2024-12-04T05:30+0000",
          "height": -0.121
        },
        {
          "dt": 1733292000,
          "date": "2024-12-04T06:00+0000",
          "height": -0.015
        },
        {
          "dt": 1733293800,
          "date": "2024-12-04T06:30+0000",
          "height": 0.067
        },
        {
          "dt": 1733295600,
          "date": "2024-12-04T07:00+0000",
          "height": 0.126
        },
        {
          "dt": 1733297400,
          "date": "2024-12-04T07:30+0000",
          "height": 0.159
        },
        {
          "dt": 1733299200,
          "date": "2024-12-04T08:00+0000",
          "height": 0.17
        },
        {
          "dt": 1733301000,
          "date": "2024-12-04T08:30+0000",
          "height": 0.16
        },
        {
          "dt": 1733302800,
          "date": "2024-12-04T09:00+0000",
          "height": 0.136
        },
        {
          "dt": 1733304600,
          "date": "2024-12-04T09:30+0000",
          "height": 0.102
        },
        {
          "dt": 1733306400,
          "date": "2024-12-04T10:00+0000",
          "height": 0.065
        },
        {
          "dt": 1733308200,
          "date": "2024-12-04T10:30+0000",
          "height": 0.032
        },
        {
          "dt": 1733310000,
          "date": "2024-12-04T11:00+0000",
          "height": 0.008
        },
        {
          "dt": 1733311800,
          "date": "2024-12-04T11:30+0000",
          "height": -0.002
        },
        {
          "dt": 1733313600,
          "date": "2024-12-04T12:00+0000",
          "height": 0.007
        },
        {
          "dt": 1733315400,
          "date": "2024-12-04T12:30+0000",
          "height": 0.038
        },
        {
          "dt": 1733317200,
          "date": "2024-12-04T13:00+0000",
          "height": 0.091
        },
        {
          "dt": 1733319000,
          "date": "2024-12-04T13:30+0000",
          "height": 0.165
        },
        {
          "dt": 1733320800,
          "date": "2024-12-04T14:00+0000",
          "height": 0.257
        },
        {
          "dt": 1733322600,
          "date": "2024-12-04T14:30+0000",
          "height": 0.363
        },
        {
          "dt": 1733324400,
          "date": "2024-12-04T15:00+0000",
          "height": 0.478
        },
        {
          "dt": 1733326200,
          "date": "2024-12-04T15:30+0000",
          "height": 0.593
        },
        {
          "dt": 1733328000,
          "date": "2024-12-04T16:00+0000",
          "height": 0.703
        },
        {
          "dt": 1733329800,
          "date": "2024-12-04T16:30+0000",
          "height": 0.799
        },
        {
          "dt": 1733331600,
          "date": "2024-12-04T17:00+0000",
          "height": 0.876
        },
        {
          "dt": 1733333400,
          "date": "2024-12-04T17:30+0000",
          "height": 0.926
        },
        {
          "dt": 1733335200,
          "date": "2024-12-04T18:00+0000",
          "height": 0.945
        },
        {
          "dt": 1733337000,
          "date": "2024-12-04T18:30+0000",
          "height": 0.929
        },
        {
          "dt": 1733338800,
          "date": "2024-12-04T19:00+0000",
          "height": 0.878
        },
        {
          "dt": 1733340600,
          "date": "2024-12-04T19:30+0000",
          "height": 0.791
        },
        {
          "dt": 1733342400,
          "date": "2024-12-04T20:00+0000",
          "height": 0.671
        },
        {
          "dt": 1733344200,
          "date": "2024-12-04T20:30+0000",
          "height": 0.521
        },
        {
          "dt": 1733346000,
          "date": "2024-12-04T21:00+0000",
          "height": 0.348
        },
        {
          "dt": 1733347800,
          "date": "2024-12-04T21:30+0000",
          "height": 0.158
        },
        {
          "dt": 1733349600,
          "date": "2024-12-04T22:00+0000",
          "height": -0.04
        },
        {
          "dt": 1733351400,
          "date": "2024-12-04T22:30+0000",
          "height": -0.239
        },
        {
          "dt": 1733353200,
          "date": "2024-12-04T23:00+0000",
          "height": -0.429
        },
        {
          "dt": 1733355000,
          "date": "2024-12-04T23:30+0000",
          "height": -0.602
        },
        {
          "dt": 1733356800,
          "date": "2024-12-05T00:00+0000",
          "height": -0.751
        },
        {
          "dt": 1733358600,
          "date": "2024-12-05T00:30+0000",
          "height": -0.868
        },
        {
          "dt": 1733360400,
          "date": "2024-12-05T01:00+0000",
          "height": -0.951
        },
        {
          "dt": 1733362200,
          "date": "2024-12-05T01:30+0000",
          "height": -0.996
        },
        {
          "dt": 1733364000,
          "date": "2024-12-05T02:00+0000",
          "height": -1.003
        },
        {
          "dt": 1733365800,
          "date": "2024-12-05T02:30+0000",
          "height": -0.974
        },
        {
          "dt": 1733367600,
          "date": "2024-12-05T03:00+0000",
          "height": -0.912
        },
        {
          "dt": 1733369400,
          "date": "2024-12-05T03:30+0000",
          "height": -0.822
        },
        {
          "dt": 1733371200,
          "date": "2024-12-05T04:00+0000",
          "height": -0.711
        },
        {
          "dt": 1733373000,
          "date": "2024-12-05T04:30+0000",
          "height": -0.585
        },
        {
          "dt": 1733374800,
          "date": "2024-12-05T05:00+0000",
          "height": -0.452
        },
        {
          "dt": 1733376600,
          "date": "2024-12-05T05:30+0000",
          "height": -0.32
        },
        {
          "dt": 1733378400,
          "date": "2024-12-05T06:00+0000",
          "height": -0.194
        },
        {
          "dt": 1733380200,
          "date": "2024-12-05T06:30+0000",
          "height": -0.081
        },
        {
          "dt": 1733382000,
          "date": "2024-12-05T07:00+0000",
          "height": 0.014
        },
        {
          "dt": 1733383800,
          "date": "2024-12-05T07:30+0000",
          "height": 0.089
        },
        {
          "dt": 1733385600,
          "date": "2024-12-05T08:00+0000",
          "height": 0.141
        },
        {
          "dt": 1733387400,
          "date": "2024-12-05T08:30+0000",
          "height": 0.171
        },
        {
          "dt": 1733389200,
          "date": "2024-12-05T09:00+0000",
          "height": 0.18
        },
        {
          "dt": 1733391000,
          "date": "2024-12-05T09:30+0000",
          "height": 0.172
        },
        {
          "dt": 1733392800,
          "date": "2024-12-05T10:00+0000",
          "height": 0.15
        },
        {
          "dt": 1733394600,
          "date": "2024-12-05T10:30+0000",
          "height": 0.121
        },
        {
          "dt": 1733396400,
          "date": "2024-12-05T11:00+0000",
          "height": 0.09
        },
        {
          "dt": 1733398200,
          "date": "2024-12-05T11:30+0000",
          "height": 0.063
        },
        {
          "dt": 1733400000,
          "date": "2024-12-05T12:00+0000",
          "height": 0.047
        },
        {
          "dt": 1733401800,
          "date": "2024-12-05T12:30+0000",
          "height": 0.044
        },
        {
          "dt": 1733403600,
          "date": "2024-12-05T13:00+0000",
          "height": 0.059
        },
        {
          "dt": 1733405400,
          "date": "2024-12-05T13:30+0000",
          "height": 0.094
        },
        {
          "dt": 1733407200,
          "date": "2024-12-05T14:00+0000",
          "height": 0.148
        },
        {
          "dt": 1733409000,
          "date": "2024-12-05T14:30+0000",
          "height": 0.219
        }
      ]
    }
  },
  {
    "id": 3,
    "lat": 33.7701,
    "lng": -118.1937,
    "info": "Long Beach",
    "wiki": "Long_Beach,_California",
    "data": {
      "status": 200,
      "callCount": 1,
      "copyright": "Tidal data retrieved from www.worldtides.info. Copyright (c) 2014-2021 Brainware LLC. Licensed for use of individual spatial coordinates on behalf of/by an end-user. Source data created by the Center for Operational Oceanographic Products and Services (CO-OPS) and is not subject to copyright protection. NO GUARANTEES ARE MADE ABOUT THE CORRECTNESS OF THIS DATA. You may not use it if anyone or anything could come to harm as a result of using it (e.g. for navigational purposes).",
      "requestLat": 33.7701,
      "requestLon": -118.1937,
      "responseLat": 33.7717,
      "responseLon": -118.21,
      "atlas": "NOAA",
      "station": "Long Beach, Inner Harbor, California",
      "heights": [
        {
          "dt": 1733236200,
          "date": "2024-12-03T14:30+0000",
          "height": 0.497
        },
        {
          "dt": 1733238000,
          "date": "2024-12-03T15:00+0000",
          "height": 0.625
        },
        {
          "dt": 1733239800,
          "date": "2024-12-03T15:30+0000",
          "height": 0.745
        },
        {
          "dt": 1733241600,
          "date": "2024-12-03T16:00+0000",
          "height": 0.847
        },
        {
          "dt": 1733243400,
          "date": "2024-12-03T16:30+0000",
          "height": 0.926
        },
        {
          "dt": 1733245200,
          "date": "2024-12-03T17:00+0000",
          "height": 0.975
        },
        {
          "dt": 1733247000,
          "date": "2024-12-03T17:30+0000",
          "height": 0.99
        },
        {
          "dt": 1733248800,
          "date": "2024-12-03T18:00+0000",
          "height": 0.968
        },
        {
          "dt": 1733250600,
          "date": "2024-12-03T18:30+0000",
          "height": 0.907
        },
        {
          "dt": 1733252400,
          "date": "2024-12-03T19:00+0000",
          "height": 0.809
        },
        {
          "dt": 1733254200,
          "date": "2024-12-03T19:30+0000",
          "height": 0.677
        },
        {
          "dt": 1733256000,
          "date": "2024-12-03T20:00+0000",
          "height": 0.517
        },
        {
          "dt": 1733257800,
          "date": "2024-12-03T20:30+0000",
          "height": 0.335
        },
        {
          "dt": 1733259600,
          "date": "2024-12-03T21:00+0000",
          "height": 0.138
        },
        {
          "dt": 1733261400,
          "date": "2024-12-03T21:30+0000",
          "height": -0.064
        },
        {
          "dt": 1733263200,
          "date": "2024-12-03T22:00+0000",
          "height": -0.262
        },
        {
          "dt": 1733265000,
          "date": "2024-12-03T22:30+0000",
          "height": -0.447
        },
        {
          "dt": 1733266800,
          "date": "2024-12-03T23:00+0000",
          "height": -0.613
        },
        {
          "dt": 1733268600,
          "date": "2024-12-03T23:30+0000",
          "height": -0.75
        },
        {
          "dt": 1733270400,
          "date": "2024-12-04T00:00+0000",
          "height": -0.855
        },
        {
          "dt": 1733272200,
          "date": "2024-12-04T00:30+0000",
          "height": -0.923
        },
        {
          "dt": 1733274000,
          "date": "2024-12-04T01:00+0000",
          "height": -0.952
        },
        {
          "dt": 1733275800,
          "date": "2024-12-04T01:30+0000",
          "height": -0.945
        },
        {
          "dt": 1733277600,
          "date": "2024-12-04T02:00+0000",
          "height": -0.902
        },
        {
          "dt": 1733279400,
          "date": "2024-12-04T02:30+0000",
          "height": -0.828
        },
        {
          "dt": 1733281200,
          "date": "2024-12-04T03:00+0000",
          "height": -0.73
        },
        {
          "dt": 1733283000,
          "date": "2024-12-04T03:30+0000",
          "height": -0.613
        },
        {
          "dt": 1733284800,
          "date": "2024-12-04T04:00+0000",
          "height": -0.487
        },
        {
          "dt": 1733286600,
          "date": "2024-12-04T04:30+0000",
          "height": -0.358
        },
        {
          "dt": 1733288400,
          "date": "2024-12-04T05:00+0000",
          "height": -0.234
        },
        {
          "dt": 1733290200,
          "date": "2024-12-04T05:30+0000",
          "height": -0.122
        },
        {
          "dt": 1733292000,
          "date": "2024-12-04T06:00+0000",
          "height": -0.027
        },
        {
          "dt": 1733293800,
          "date": "2024-12-04T06:30+0000",
          "height": 0.047
        },
        {
          "dt": 1733295600,
          "date": "2024-12-04T07:00+0000",
          "height": 0.098
        },
        {
          "dt": 1733297400,
          "date": "2024-12-04T07:30+0000",
          "height": 0.126
        },
        {
          "dt": 1733299200,
          "date": "2024-12-04T08:00+0000",
          "height": 0.133
        },
        {
          "dt": 1733301000,
          "date": "2024-12-04T08:30+0000",
          "height": 0.12
        },
        {
          "dt": 1733302800,
          "date": "2024-12-04T09:00+0000",
          "height": 0.095
        },
        {
          "dt": 1733304600,
          "date": "2024-12-04T09:30+0000",
          "height": 0.06
        },
        {
          "dt": 1733306400,
          "date": "2024-12-04T10:00+0000",
          "height": 0.024
        },
        {
          "dt": 1733308200,
          "date": "2024-12-04T10:30+0000",
          "height": -0.009
        },
        {
          "dt": 1733310000,
          "date": "2024-12-04T11:00+0000",
          "height": -0.031
        },
        {
          "dt": 1733311800,
          "date": "2024-12-04T11:30+0000",
          "height": -0.039
        },
        {
          "dt": 1733313600,
          "date": "2024-12-04T12:00+0000",
          "height": -0.028
        },
        {
          "dt": 1733315400,
          "date": "2024-12-04T12:30+0000",
          "height": 0.004
        },
        {
          "dt": 1733317200,
          "date": "2024-12-04T13:00+0000",
          "height": 0.058
        },
        {
          "dt": 1733319000,
          "date": "2024-12-04T13:30+0000",
          "height": 0.133
        },
        {
          "dt": 1733320800,
          "date": "2024-12-04T14:00+0000",
          "height": 0.225
        },
        {
          "dt": 1733322600,
          "date": "2024-12-04T14:30+0000",
          "height": 0.332
        },
        {
          "dt": 1733324400,
          "date": "2024-12-04T15:00+0000",
          "height": 0.446
        },
        {
          "dt": 1733326200,
          "date": "2024-12-04T15:30+0000",
          "height": 0.563
        },
        {
          "dt": 1733328000,
          "date": "2024-12-04T16:00+0000",
          "height": 0.674
        },
        {
          "dt": 1733329800,
          "date": "2024-12-04T16:30+0000",
          "height": 0.772
        },
        {
          "dt": 1733331600,
          "date": "2024-12-04T17:00+0000",
          "height": 0.852
        },
        {
          "dt": 1733333400,
          "date": "2024-12-04T17:30+0000",
          "height": 0.906
        },
        {
          "dt": 1733335200,
          "date": "2024-12-04T18:00+0000",
          "height": 0.93
        },
        {
          "dt": 1733337000,
          "date": "2024-12-04T18:30+0000",
          "height": 0.922
        },
        {
          "dt": 1733338800,
          "date": "2024-12-04T19:00+0000",
          "height": 0.878
        },
        {
          "dt": 1733340600,
          "date": "2024-12-04T19:30+0000",
          "height": 0.8
        },
        {
          "dt": 1733342400,
          "date": "2024-12-04T20:00+0000",
          "height": 0.69
        },
        {
          "dt": 1733344200,
          "date": "2024-12-04T20:30+0000",
          "height": 0.551
        },
        {
          "dt": 1733346000,
          "date": "2024-12-04T21:00+0000",
          "height": 0.388
        },
        {
          "dt": 1733347800,
          "date": "2024-12-04T21:30+0000",
          "height": 0.21
        },
        {
          "dt": 1733349600,
          "date": "2024-12-04T22:00+0000",
          "height": 0.022
        },
        {
          "dt": 1733351400,
          "date": "2024-12-04T22:30+0000",
          "height": -0.166
        },
        {
          "dt": 1733353200,
          "date": "2024-12-04T23:00+0000",
          "height": -0.347
        },
        {
          "dt": 1733355000,
          "date": "2024-12-04T23:30+0000",
          "height": -0.512
        },
        {
          "dt": 1733356800,
          "date": "2024-12-05T00:00+0000",
          "height": -0.655
        },
        {
          "dt": 1733358600,
          "date": "2024-12-05T00:30+0000",
          "height": -0.77
        },
        {
          "dt": 1733360400,
          "date": "2024-12-05T01:00+0000",
          "height": -0.853
        },
        {
          "dt": 1733362200,
          "date": "2024-12-05T01:30+0000",
          "height": -0.901
        },
        {
          "dt": 1733364000,
          "date": "2024-12-05T02:00+0000",
          "height": -0.914
        },
        {
          "dt": 1733365800,
          "date": "2024-12-05T02:30+0000",
          "height": -0.892
        },
        {
          "dt": 1733367600,
          "date": "2024-12-05T03:00+0000",
          "height": -0.84
        },
        {
          "dt": 1733369400,
          "date": "2024-12-05T03:30+0000",
          "height": -0.761
        },
        {
          "dt": 1733371200,
          "date": "2024-12-05T04:00+0000",
          "height": -0.661
        },
        {
          "dt": 1733373000,
          "date": "2024-12-05T04:30+0000",
          "height": -0.547
        },
        {
          "dt": 1733374800,
          "date": "2024-12-05T05:00+0000",
          "height": -0.426
        },
        {
          "dt": 1733376600,
          "date": "2024-12-05T05:30+0000",
          "height": -0.305
        },
        {
          "dt": 1733378400,
          "date": "2024-12-05T06:00+0000",
          "height": -0.19
        },
        {
          "dt": 1733380200,
          "date": "2024-12-05T06:30+0000",
          "height": -0.088
        },
        {
          "dt": 1733382000,
          "date": "2024-12-05T07:00+0000",
          "height": -0.002
        },
        {
          "dt": 1733383800,
          "date": "2024-12-05T07:30+0000",
          "height": 0.064
        },
        {
          "dt": 1733385600,
          "date": "2024-12-05T08:00+0000",
          "height": 0.11
        },
        {
          "dt": 1733387400,
          "date": "2024-12-05T08:30+0000",
          "height": 0.134
        },
        {
          "dt": 1733389200,
          "date": "2024-12-05T09:00+0000",
          "height": 0.139
        },
        {
          "dt": 1733391000,
          "date": "2024-12-05T09:30+0000",
          "height": 0.129
        },
        {
          "dt": 1733392800,
          "date": "2024-12-05T10:00+0000",
          "height": 0.108
        },
        {
          "dt": 1733394600,
          "date": "2024-12-05T10:30+0000",
          "height": 0.08
        },
        {
          "dt": 1733396400,
          "date": "2024-12-05T11:00+0000",
          "height": 0.051
        },
        {
          "dt": 1733398200,
          "date": "2024-12-05T11:30+0000",
          "height": 0.027
        },
        {
          "dt": 1733400000,
          "date": "2024-12-05T12:00+0000",
          "height": 0.012
        },
        {
          "dt": 1733401800,
          "date": "2024-12-05T12:30+0000",
          "height": 0.011
        },
        {
          "dt": 1733403600,
          "date": "2024-12-05T13:00+0000",
          "height": 0.027
        },
        {
          "dt": 1733405400,
          "date": "2024-12-05T13:30+0000",
          "height": 0.061
        },
        {
          "dt": 1733407200,
          "date": "2024-12-05T14:00+0000",
          "height": 0.114
        },
        {
          "dt": 1733409000,
          "date": "2024-12-05T14:30+0000",
          "height": 0.183
        }
      ]
    }
  },
  {
    "id": 4,
    "lat": 33.5427,
    "lng": -117.7854,
    "info": "Laguna Beach",
    "wiki": "Laguna_Beach,_California",
    "data": {
      "status": 200,
      "callCount": 1,
      "copyright": "Tidal data retrieved from www.worldtides.info. Copyright (c) 2014-2021 Brainware LLC. Licensed for use of individual spatial coordinates on behalf of/by an end-user. Copyright (c) Oregon State University. Licensed for individual spatial coordinates via ModEM-Geophysics Inc. NO GUARANTEES ARE MADE ABOUT THE CORRECTNESS OF THIS DATA. You may not use it if anyone or anything could come to harm as a result of using it (e.g. for navigational purposes).",
      "requestLat": 33.5427,
      "requestLon": -117.7854,
      "responseLat": 33.5,
      "responseLon": -117.833,
      "atlas": "TPXO",
      "heights": [
        {
          "dt": 1733236200,
          "date": "2024-12-03T14:30+0000",
          "height": 0.576
        },
        {
          "dt": 1733238000,
          "date": "2024-12-03T15:00+0000",
          "height": 0.705
        },
        {
          "dt": 1733239800,
          "date": "2024-12-03T15:30+0000",
          "height": 0.823
        },
        {
          "dt": 1733241600,
          "date": "2024-12-03T16:00+0000",
          "height": 0.922
        },
        {
          "dt": 1733243400,
          "date": "2024-12-03T16:30+0000",
          "height": 0.993
        },
        {
          "dt": 1733245200,
          "date": "2024-12-03T17:00+0000",
          "height": 1.031
        },
        {
          "dt": 1733247000,
          "date": "2024-12-03T17:30+0000",
          "height": 1.03
        },
        {
          "dt": 1733248800,
          "date": "2024-12-03T18:00+0000",
          "height": 0.988
        },
        {
          "dt": 1733250600,
          "date": "2024-12-03T18:30+0000",
          "height": 0.905
        },
        {
          "dt": 1733252400,
          "date": "2024-12-03T19:00+0000",
          "height": 0.783
        },
        {
          "dt": 1733254200,
          "date": "2024-12-03T19:30+0000",
          "height": 0.625
        },
        {
          "dt": 1733256000,
          "date": "2024-12-03T20:00+0000",
          "height": 0.439
        },
        {
          "dt": 1733257800,
          "date": "2024-12-03T20:30+0000",
          "height": 0.232
        },
        {
          "dt": 1733259600,
          "date": "2024-12-03T21:00+0000",
          "height": 0.014
        },
        {
          "dt": 1733261400,
          "date": "2024-12-03T21:30+0000",
          "height": -0.206
        },
        {
          "dt": 1733263200,
          "date": "2024-12-03T22:00+0000",
          "height": -0.417
        },
        {
          "dt": 1733265000,
          "date": "2024-12-03T22:30+0000",
          "height": -0.611
        },
        {
          "dt": 1733266800,
          "date": "2024-12-03T23:00+0000",
          "height": -0.779
        },
        {
          "dt": 1733268600,
          "date": "2024-12-03T23:30+0000",
          "height": -0.915
        },
        {
          "dt": 1733270400,
          "date": "2024-12-04T00:00+0000",
          "height": -1.013
        },
        {
          "dt": 1733272200,
          "date": "2024-12-04T00:30+0000",
          "height": -1.071
        },
        {
          "dt": 1733274000,
          "date": "2024-12-04T01:00+0000",
          "height": -1.088
        },
        {
          "dt": 1733275800,
          "date": "2024-12-04T01:30+0000",
          "height": -1.066
        },
        {
          "dt": 1733277600,
          "date": "2024-12-04T02:00+0000",
          "height": -1.006
        },
        {
          "dt": 1733279400,
          "date": "2024-12-04T02:30+0000",
          "height": -0.915
        },
        {
          "dt": 1733281200,
          "date": "2024-12-04T03:00+0000",
          "height": -0.799
        },
        {
          "dt": 1733283000,
          "date": "2024-12-04T03:30+0000",
          "height": -0.666
        },
        {
          "dt": 1733284800,
          "date": "2024-12-04T04:00+0000",
          "height": -0.522
        },
        {
          "dt": 1733286600,
          "date": "2024-12-04T04:30+0000",
          "height": -0.378
        },
        {
          "dt": 1733288400,
          "date": "2024-12-04T05:00+0000",
          "height": -0.241
        },
        {
          "dt": 1733290200,
          "date": "2024-12-04T05:30+0000",
          "height": -0.118
        },
        {
          "dt": 1733292000,
          "date": "2024-12-04T06:00+0000",
          "height": -0.014
        },
        {
          "dt": 1733293800,
          "date": "2024-12-04T06:30+0000",
          "height": 0.065
        },
        {
          "dt": 1733295600,
          "date": "2024-12-04T07:00+0000",
          "height": 0.119
        },
        {
          "dt": 1733297400,
          "date": "2024-12-04T07:30+0000",
          "height": 0.147
        },
        {
          "dt": 1733299200,
          "date": "2024-12-04T08:00+0000",
          "height": 0.152
        },
        {
          "dt": 1733301000,
          "date": "2024-12-04T08:30+0000",
          "height": 0.137
        },
        {
          "dt": 1733302800,
          "date": "2024-12-04T09:00+0000",
          "height": 0.108
        },
        {
          "dt": 1733304600,
          "date": "2024-12-04T09:30+0000",
          "height": 0.071
        },
        {
          "dt": 1733306400,
          "date": "2024-12-04T10:00+0000",
          "height": 0.033
        },
        {
          "dt": 1733308200,
          "date": "2024-12-04T10:30+0000",
          "height": 0.001
        },
        {
          "dt": 1733310000,
          "date": "2024-12-04T11:00+0000",
          "height": -0.02
        },
        {
          "dt": 1733311800,
          "date": "2024-12-04T11:30+0000",
          "height": -0.025
        },
        {
          "dt": 1733313600,
          "date": "2024-12-04T12:00+0000",
          "height": -0.01
        },
        {
          "dt": 1733315400,
          "date": "2024-12-04T12:30+0000",
          "height": 0.026
        },
        {
          "dt": 1733317200,
          "date": "2024-12-04T13:00+0000",
          "height": 0.085
        },
        {
          "dt": 1733319000,
          "date": "2024-12-04T13:30+0000",
          "height": 0.165
        },
        {
          "dt": 1733320800,
          "date": "2024-12-04T14:00+0000",
          "height": 0.263
        },
        {
          "dt": 1733322600,
          "date": "2024-12-04T14:30+0000",
          "height": 0.375
        },
        {
          "dt": 1733324400,
          "date": "2024-12-04T15:00+0000",
          "height": 0.493
        },
        {
          "dt": 1733326200,
          "date": "2024-12-04T15:30+0000",
          "height": 0.613
        },
        {
          "dt": 1733328000,
          "date": "2024-12-04T16:00+0000",
          "height": 0.726
        },
        {
          "dt": 1733329800,
          "date": "2024-12-04T16:30+0000",
          "height": 0.824
        },
        {
          "dt": 1733331600,
          "date": "2024-12-04T17:00+0000",
          "height": 0.901
        },
        {
          "dt": 1733333400,
          "date": "2024-12-04T17:30+0000",
          "height": 0.95
        },
        {
          "dt": 1733335200,
          "date": "2024-12-04T18:00+0000",
          "height": 0.965
        },
        {
          "dt": 1733337000,
          "date": "2024-12-04T18:30+0000",
          "height": 0.943
        },
        {
          "dt": 1733338800,
          "date": "2024-12-04T19:00+0000",
          "height": 0.883
        },
        {
          "dt": 1733340600,
          "date": "2024-12-04T19:30+0000",
          "height": 0.785
        },
        {
          "dt": 1733342400,
          "date": "2024-12-04T20:00+0000",
          "height": 0.651
        },
        {
          "dt": 1733344200,
          "date": "2024-12-04T20:30+0000",
          "height": 0.488
        },
        {
          "dt": 1733346000,
          "date": "2024-12-04T21:00+0000",
          "height": 0.302
        },
        {
          "dt": 1733347800,
          "date": "2024-12-04T21:30+0000",
          "height": 0.1
        },
        {
          "dt": 1733349600,
          "date": "2024-12-04T22:00+0000",
          "height": -0.107
        },
        {
          "dt": 1733351400,
          "date": "2024-12-04T22:30+0000",
          "height": -0.312
        },
        {
          "dt": 1733353200,
          "date": "2024-12-04T23:00+0000",
          "height": -0.504
        },
        {
          "dt": 1733355000,
          "date": "2024-12-04T23:30+0000",
          "height": -0.676
        },
        {
          "dt": 1733356800,
          "date": "2024-12-05T00:00+0000",
          "height": -0.821
        },
        {
          "dt": 1733358600,
          "date": "2024-12-05T00:30+0000",
          "height": -0.932
        },
        {
          "dt": 1733360400,
          "date": "2024-12-05T01:00+0000",
          "height": -1.008
        },
        {
          "dt": 1733362200,
          "date": "2024-12-05T01:30+0000",
          "height": -1.045
        },
        {
          "dt": 1733364000,
          "date": "2024-12-05T02:00+0000",
          "height": -1.043
        },
        {
          "dt": 1733365800,
          "date": "2024-12-05T02:30+0000",
          "height": -1.005
        },
        {
          "dt": 1733367600,
          "date": "2024-12-05T03:00+0000",
          "height": -0.934
        },
        {
          "dt": 1733369400,
          "date": "2024-12-05T03:30+0000",
          "height": -0.835
        },
        {
          "dt": 1733371200,
          "date": "2024-12-05T04:00+0000",
          "height": -0.714
        },
        {
          "dt": 1733373000,
          "date": "2024-12-05T04:30+0000",
          "height": -0.58
        },
        {
          "dt": 1733374800,
          "date": "2024-12-05T05:00+0000",
          "height": -0.439
        },
        {
          "dt": 1733376600,
          "date": "2024-12-05T05:30+0000",
          "height": -0.3
        },
        {
          "dt": 1733378400,
          "date": "2024-12-05T06:00+0000",
          "height": -0.17
        },
        {
          "dt": 1733380200,
          "date": "2024-12-05T06:30+0000",
          "height": -0.055
        },
        {
          "dt": 1733382000,
          "date": "2024-12-05T07:00+0000",
          "height": 0.039
        },
        {
          "dt": 1733383800,
          "date": "2024-12-05T07:30+0000",
          "height": 0.11
        },
        {
          "dt": 1733385600,
          "date": "2024-12-05T08:00+0000",
          "height": 0.157
        },
        {
          "dt": 1733387400,
          "date": "2024-12-05T08:30+0000",
          "height": 0.179
        },
        {
          "dt": 1733389200,
          "date": "2024-12-05T09:00+0000",
          "height": 0.179
        },
        {
          "dt": 1733391000,
          "date": "2024-12-05T09:30+0000",
          "height": 0.162
        },
        {
          "dt": 1733392800,
          "date": "2024-12-05T10:00+0000",
          "height": 0.133
        },
        {
          "dt": 1733394600,
          "date": "2024-12-05T10:30+0000",
          "height": 0.097
        },
        {
          "dt": 1733396400,
          "date": "2024-12-05T11:00+0000",
          "height": 0.061
        },
        {
          "dt": 1733398200,
          "date": "2024-12-05T11:30+0000",
          "height": 0.031
        },
        {
          "dt": 1733400000,
          "date": "2024-12-05T12:00+0000",
          "height": 0.011
        },
        {
          "dt": 1733401800,
          "date": "2024-12-05T12:30+0000",
          "height": 0.007
        },
        {
          "dt": 1733403600,
          "date": "2024-12-05T13:00+0000",
          "height": 0.021
        },
        {
          "dt": 1733405400,
          "date": "2024-12-05T13:30+0000",
          "height": 0.054
        },
        {
          "dt": 1733407200,
          "date": "2024-12-05T14:00+0000",
          "height": 0.107
        },
        {
          "dt": 1733409000,
          "date": "2024-12-05T14:30+0000",
          "height": 0.178
        }
      ]
    }
  },
  {
    "id": 5,
    "lat": 33.6189,
    "lng": -117.9298,
    "info": "Newport Beach",
    "wiki": "Newport_Beach,_California",
    "data": {
      "status": 200,
      "callCount": 1,
      "copyright": "Tidal data retrieved from www.worldtides.info. Copyright (c) 2014-2021 Brainware LLC. Licensed for use of individual spatial coordinates on behalf of/by an end-user. Source data created by the Center for Operational Oceanographic Products and Services (CO-OPS) and is not subject to copyright protection. NO GUARANTEES ARE MADE ABOUT THE CORRECTNESS OF THIS DATA. You may not use it if anyone or anything could come to harm as a result of using it (e.g. for navigational purposes).",
      "requestLat": 33.6189,
      "requestLon": -117.9298,
      "responseLat": 33.63,
      "responseLon": -117.958,
      "atlas": "NOAA",
      "station": "Santa Ana River entrance (inside), California",
      "heights": [
        {
          "dt": 1733236200,
          "date": "2024-12-03T14:30+0000",
          "height": -0.017
        },
        {
          "dt": 1733238000,
          "date": "2024-12-03T15:00+0000",
          "height": 0.064
        },
        {
          "dt": 1733239800,
          "date": "2024-12-03T15:30+0000",
          "height": 0.153
        },
        {
          "dt": 1733241600,
          "date": "2024-12-03T16:00+0000",
          "height": 0.243
        },
        {
          "dt": 1733243400,
          "date": "2024-12-03T16:30+0000",
          "height": 0.331
        },
        {
          "dt": 1733245200,
          "date": "2024-12-03T17:00+0000",
          "height": 0.411
        },
        {
          "dt": 1733247000,
          "date": "2024-12-03T17:30+0000",
          "height": 0.478
        },
        {
          "dt": 1733248800,
          "date": "2024-12-03T18:00+0000",
          "height": 0.527
        },
        {
          "dt": 1733250600,
          "date": "2024-12-03T18:30+0000",
          "height": 0.554
        },
        {
          "dt": 1733252400,
          "date": "2024-12-03T19:00+0000",
          "height": 0.558
        },
        {
          "dt": 1733254200,
          "date": "2024-12-03T19:30+0000",
          "height": 0.538
        },
        {
          "dt": 1733256000,
          "date": "2024-12-03T20:00+0000",
          "height": 0.493
        },
        {
          "dt": 1733257800,
          "date": "2024-12-03T20:30+0000",
          "height": 0.427
        },
        {
          "dt": 1733259600,
          "date": "2024-12-03T21:00+0000",
          "height": 0.341
        },
        {
          "dt": 1733261400,
          "date": "2024-12-03T21:30+0000",
          "height": 0.24
        },
        {
          "dt": 1733263200,
          "date": "2024-12-03T22:00+0000",
          "height": 0.13
        },
        {
          "dt": 1733265000,
          "date": "2024-12-03T22:30+0000",
          "height": 0.017
        },
        {
          "dt": 1733266800,
          "date": "2024-12-03T23:00+0000",
          "height": -0.095
        },
        {
          "dt": 1733268600,
          "date": "2024-12-03T23:30+0000",
          "height": -0.198
        },
        {
          "dt": 1733270400,
          "date": "2024-12-04T00:00+0000",
          "height": -0.289
        },
        {
          "dt": 1733272200,
          "date": "2024-12-04T00:30+0000",
          "height": -0.362
        },
        {
          "dt": 1733274000,
          "date": "2024-12-04T01:00+0000",
          "height": -0.414
        },
        {
          "dt": 1733275800,
          "date": "2024-12-04T01:30+0000",
          "height": -0.445
        },
        {
          "dt": 1733277600,
          "date": "2024-12-04T02:00+0000",
          "height": -0.452
        },
        {
          "dt": 1733279400,
          "date": "2024-12-04T02:30+0000",
          "height": -0.438
        },
        {
          "dt": 1733281200,
          "date": "2024-12-04T03:00+0000",
          "height": -0.404
        },
        {
          "dt": 1733283000,
          "date": "2024-12-04T03:30+0000",
          "height": -0.354
        },
        {
          "dt": 1733284800,
          "date": "2024-12-04T04:00+0000",
          "height": -0.292
        },
        {
          "dt": 1733286600,
          "date": "2024-12-04T04:30+0000",
          "height": -0.222
        },
        {
          "dt": 1733288400,
          "date": "2024-12-04T05:00+0000",
          "height": -0.15
        },
        {
          "dt": 1733290200,
          "date": "2024-12-04T05:30+0000",
          "height": -0.081
        },
        {
          "dt": 1733292000,
          "date": "2024-12-04T06:00+0000",
          "height": -0.018
        },
        {
          "dt": 1733293800,
          "date": "2024-12-04T06:30+0000",
          "height": 0.035
        },
        {
          "dt": 1733295600,
          "date": "2024-12-04T07:00+0000",
          "height": 0.074
        },
        {
          "dt": 1733297400,
          "date": "2024-12-04T07:30+0000",
          "height": 0.098
        },
        {
          "dt": 1733299200,
          "date": "2024-12-04T08:00+0000",
          "height": 0.106
        },
        {
          "dt": 1733301000,
          "date": "2024-12-04T08:30+0000",
          "height": 0.099
        },
        {
          "dt": 1733302800,
          "date": "2024-12-04T09:00+0000",
          "height": 0.078
        },
        {
          "dt": 1733304600,
          "date": "2024-12-04T09:30+0000",
          "height": 0.046
        },
        {
          "dt": 1733306400,
          "date": "2024-12-04T10:00+0000",
          "height": 0.006
        },
        {
          "dt": 1733308200,
          "date": "2024-12-04T10:30+0000",
          "height": -0.038
        },
        {
          "dt": 1733310000,
          "date": "2024-12-04T11:00+0000",
          "height": -0.082
        },
        {
          "dt": 1733311800,
          "date": "2024-12-04T11:30+0000",
          "height": -0.123
        },
        {
          "dt": 1733313600,
          "date": "2024-12-04T12:00+0000",
          "height": -0.155
        },
        {
          "dt": 1733315400,
          "date": "2024-12-04T12:30+0000",
          "height": -0.176
        },
        {
          "dt": 1733317200,
          "date": "2024-12-04T13:00+0000",
          "height": -0.183
        },
        {
          "dt": 1733319000,
          "date": "2024-12-04T13:30+0000",
          "height": -0.174
        },
        {
          "dt": 1733320800,
          "date": "2024-12-04T14:00+0000",
          "height": -0.148
        },
        {
          "dt": 1733322600,
          "date": "2024-12-04T14:30+0000",
          "height": -0.106
        },
        {
          "dt": 1733324400,
          "date": "2024-12-04T15:00+0000",
          "height": -0.049
        },
        {
          "dt": 1733326200,
          "date": "2024-12-04T15:30+0000",
          "height": 0.021
        },
        {
          "dt": 1733328000,
          "date": "2024-12-04T16:00+0000",
          "height": 0.1
        },
        {
          "dt": 1733329800,
          "date": "2024-12-04T16:30+0000",
          "height": 0.184
        },
        {
          "dt": 1733331600,
          "date": "2024-12-04T17:00+0000",
          "height": 0.267
        },
        {
          "dt": 1733333400,
          "date": "2024-12-04T17:30+0000",
          "height": 0.346
        },
        {
          "dt": 1733335200,
          "date": "2024-12-04T18:00+0000",
          "height": 0.416
        },
        {
          "dt": 1733337000,
          "date": "2024-12-04T18:30+0000",
          "height": 0.47
        },
        {
          "dt": 1733338800,
          "date": "2024-12-04T19:00+0000",
          "height": 0.507
        },
        {
          "dt": 1733340600,
          "date": "2024-12-04T19:30+0000",
          "height": 0.523
        },
        {
          "dt": 1733342400,
          "date": "2024-12-04T20:00+0000",
          "height": 0.517
        },
        {
          "dt": 1733344200,
          "date": "2024-12-04T20:30+0000",
          "height": 0.487
        },
        {
          "dt": 1733346000,
          "date": "2024-12-04T21:00+0000",
          "height": 0.436
        },
        {
          "dt": 1733347800,
          "date": "2024-12-04T21:30+0000",
          "height": 0.365
        },
        {
          "dt": 1733349600,
          "date": "2024-12-04T22:00+0000",
          "height": 0.278
        },
        {
          "dt": 1733351400,
          "date": "2024-12-04T22:30+0000",
          "height": 0.179
        },
        {
          "dt": 1733353200,
          "date": "2024-12-04T23:00+0000",
          "height": 0.073
        },
        {
          "dt": 1733355000,
          "date": "2024-12-04T23:30+0000",
          "height": -0.034
        },
        {
          "dt": 1733356800,
          "date": "2024-12-05T00:00+0000",
          "height": -0.136
        },
        {
          "dt": 1733358600,
          "date": "2024-12-05T00:30+0000",
          "height": -0.229
        },
        {
          "dt": 1733360400,
          "date": "2024-12-05T01:00+0000",
          "height": -0.308
        },
        {
          "dt": 1733362200,
          "date": "2024-12-05T01:30+0000",
          "height": -0.369
        },
        {
          "dt": 1733364000,
          "date": "2024-12-05T02:00+0000",
          "height": -0.411
        },
        {
          "dt": 1733365800,
          "date": "2024-12-05T02:30+0000",
          "height": -0.43
        },
        {
          "dt": 1733367600,
          "date": "2024-12-05T03:00+0000",
          "height": -0.429
        },
        {
          "dt": 1733369400,
          "date": "2024-12-05T03:30+0000",
          "height": -0.408
        },
        {
          "dt": 1733371200,
          "date": "2024-12-05T04:00+0000",
          "height": -0.369
        },
        {
          "dt": 1733373000,
          "date": "2024-12-05T04:30+0000",
          "height": -0.316
        },
        {
          "dt": 1733374800,
          "date": "2024-12-05T05:00+0000",
          "height": -0.254
        },
        {
          "dt": 1733376600,
          "date": "2024-12-05T05:30+0000",
          "height": -0.186
        },
        {
          "dt": 1733378400,
          "date": "2024-12-05T06:00+0000",
          "height": -0.117
        },
        {
          "dt": 1733380200,
          "date": "2024-12-05T06:30+0000",
          "height": -0.051
        },
        {
          "dt": 1733382000,
          "date": "2024-12-05T07:00+0000",
          "height": 0.007
        },
        {
          "dt": 1733383800,
          "date": "2024-12-05T07:30+0000",
          "height": 0.054
        },
        {
          "dt": 1733385600,
          "date": "2024-12-05T08:00+0000",
          "height": 0.088
        },
        {
          "dt": 1733387400,
          "date": "2024-12-05T08:30+0000",
          "height": 0.108
        },
        {
          "dt": 1733389200,
          "date": "2024-12-05T09:00+0000",
          "height": 0.113
        },
        {
          "dt": 1733391000,
          "date": "2024-12-05T09:30+0000",
          "height": 0.104
        },
        {
          "dt": 1733392800,
          "date": "2024-12-05T10:00+0000",
          "height": 0.082
        },
        {
          "dt": 1733394600,
          "date": "2024-12-05T10:30+0000",
          "height": 0.05
        },
        {
          "dt": 1733396400,
          "date": "2024-12-05T11:00+0000",
          "height": 0.012
        },
        {
          "dt": 1733398200,
          "date": "2024-12-05T11:30+0000",
          "height": -0.03
        },
        {
          "dt": 1733400000,
          "date": "2024-12-05T12:00+0000",
          "height": -0.071
        },
        {
          "dt": 1733401800,
          "date": "2024-12-05T12:30+0000",
          "height": -0.108
        },
        {
          "dt": 1733403600,
          "date": "2024-12-05T13:00+0000",
          "height": -0.137
        },
        {
          "dt": 1733405400,
          "date": "2024-12-05T13:30+0000",
          "height": -0.156
        },
        {
          "dt": 1733407200,
          "date": "2024-12-05T14:00+0000",
          "height": -0.161
        },
        {
          "dt": 1733409000,
          "date": "2024-12-05T14:30+0000",
          "height": -0.151
        }
      ]
    }
  },
  {
    "id": 6,
    "lat": 34.0381,
    "lng": -118.6923,
    "info": "Malibu Beach",
    "wiki": "Malibu,_California",
    "data": {
      "status": 200,
      "callCount": 1,
      "copyright": "Tidal data retrieved from www.worldtides.info. Copyright (c) 2014-2021 Brainware LLC. Licensed for use of individual spatial coordinates on behalf of/by an end-user. Copyright (c) Oregon State University. Licensed for individual spatial coordinates via ModEM-Geophysics Inc. NO GUARANTEES ARE MADE ABOUT THE CORRECTNESS OF THIS DATA. You may not use it if anyone or anything could come to harm as a result of using it (e.g. for navigational purposes).",
      "requestLat": 34.0381,
      "requestLon": -118.6923,
      "responseLat": 34,
      "responseLon": -118.667,
      "atlas": "TPXO",
      "heights": [
        {
          "dt": 1733236200,
          "date": "2024-12-03T14:30+0000",
          "height": 0.554
        },
        {
          "dt": 1733238000,
          "date": "2024-12-03T15:00+0000",
          "height": 0.681
        },
        {
          "dt": 1733239800,
          "date": "2024-12-03T15:30+0000",
          "height": 0.798
        },
        {
          "dt": 1733241600,
          "date": "2024-12-03T16:00+0000",
          "height": 0.899
        },
        {
          "dt": 1733243400,
          "date": "2024-12-03T16:30+0000",
          "height": 0.974
        },
        {
          "dt": 1733245200,
          "date": "2024-12-03T17:00+0000",
          "height": 1.018
        },
        {
          "dt": 1733247000,
          "date": "2024-12-03T17:30+0000",
          "height": 1.025
        },
        {
          "dt": 1733248800,
          "date": "2024-12-03T18:00+0000",
          "height": 0.993
        },
        {
          "dt": 1733250600,
          "date": "2024-12-03T18:30+0000",
          "height": 0.919
        },
        {
          "dt": 1733252400,
          "date": "2024-12-03T19:00+0000",
          "height": 0.807
        },
        {
          "dt": 1733254200,
          "date": "2024-12-03T19:30+0000",
          "height": 0.659
        },
        {
          "dt": 1733256000,
          "date": "2024-12-03T20:00+0000",
          "height": 0.481
        },
        {
          "dt": 1733257800,
          "date": "2024-12-03T20:30+0000",
          "height": 0.28
        },
        {
          "dt": 1733259600,
          "date": "2024-12-03T21:00+0000",
          "height": 0.066
        },
        {
          "dt": 1733261400,
          "date": "2024-12-03T21:30+0000",
          "height": -0.152
        },
        {
          "dt": 1733263200,
          "date": "2024-12-03T22:00+0000",
          "height": -0.364
        },
        {
          "dt": 1733265000,
          "date": "2024-12-03T22:30+0000",
          "height": -0.561
        },
        {
          "dt": 1733266800,
          "date": "2024-12-03T23:00+0000",
          "height": -0.735
        },
        {
          "dt": 1733268600,
          "date": "2024-12-03T23:30+0000",
          "height": -0.879
        },
        {
          "dt": 1733270400,
          "date": "2024-12-04T00:00+0000",
          "height": -0.988
        },
        {
          "dt": 1733272200,
          "date": "2024-12-04T00:30+0000",
          "height": -1.057
        },
        {
          "dt": 1733274000,
          "date": "2024-12-04T01:00+0000",
          "height": -1.086
        },
        {
          "dt": 1733275800,
          "date": "2024-12-04T01:30+0000",
          "height": -1.075
        },
        {
          "dt": 1733277600,
          "date": "2024-12-04T02:00+0000",
          "height": -1.028
        },
        {
          "dt": 1733279400,
          "date": "2024-12-04T02:30+0000",
          "height": -0.947
        },
        {
          "dt": 1733281200,
          "date": "2024-12-04T03:00+0000",
          "height": -0.839
        },
        {
          "dt": 1733283000,
          "date": "2024-12-04T03:30+0000",
          "height": -0.712
        },
        {
          "dt": 1733284800,
          "date": "2024-12-04T04:00+0000",
          "height": -0.573
        },
        {
          "dt": 1733286600,
          "date": "2024-12-04T04:30+0000",
          "height": -0.43
        },
        {
          "dt": 1733288400,
          "date": "2024-12-04T05:00+0000",
          "height": -0.291
        },
        {
          "dt": 1733290200,
          "date": "2024-12-04T05:30+0000",
          "height": -0.164
        },
        {
          "dt": 1733292000,
          "date": "2024-12-04T06:00+0000",
          "height": -0.054
        },
        {
          "dt": 1733293800,
          "date": "2024-12-04T06:30+0000",
          "height": 0.033
        },
        {
          "dt": 1733295600,
          "date": "2024-12-04T07:00+0000",
          "height": 0.096
        },
        {
          "dt": 1733297400,
          "date": "2024-12-04T07:30+0000",
          "height": 0.133
        },
        {
          "dt": 1733299200,
          "date": "2024-12-04T08:00+0000",
          "height": 0.147
        },
        {
          "dt": 1733301000,
          "date": "2024-12-04T08:30+0000",
          "height": 0.141
        },
        {
          "dt": 1733302800,
          "date": "2024-12-04T09:00+0000",
          "height": 0.12
        },
        {
          "dt": 1733304600,
          "date": "2024-12-04T09:30+0000",
          "height": 0.089
        },
        {
          "dt": 1733306400,
          "date": "2024-12-04T10:00+0000",
          "height": 0.055
        },
        {
          "dt": 1733308200,
          "date": "2024-12-04T10:30+0000",
          "height": 0.024
        },
        {
          "dt": 1733310000,
          "date": "2024-12-04T11:00+0000",
          "height": 0.002
        },
        {
          "dt": 1733311800,
          "date": "2024-12-04T11:30+0000",
          "height": -0.005
        },
        {
          "dt": 1733313600,
          "date": "2024-12-04T12:00+0000",
          "height": 0.006
        },
        {
          "dt": 1733315400,
          "date": "2024-12-04T12:30+0000",
          "height": 0.038
        },
        {
          "dt": 1733317200,
          "date": "2024-12-04T13:00+0000",
          "height": 0.091
        },
        {
          "dt": 1733319000,
          "date": "2024-12-04T13:30+0000",
          "height": 0.164
        },
        {
          "dt": 1733320800,
          "date": "2024-12-04T14:00+0000",
          "height": 0.255
        },
        {
          "dt": 1733322600,
          "date": "2024-12-04T14:30+0000",
          "height": 0.361
        },
        {
          "dt": 1733324400,
          "date": "2024-12-04T15:00+0000",
          "height": 0.475
        },
        {
          "dt": 1733326200,
          "date": "2024-12-04T15:30+0000",
          "height": 0.591
        },
        {
          "dt": 1733328000,
          "date": "2024-12-04T16:00+0000",
          "height": 0.703
        },
        {
          "dt": 1733329800,
          "date": "2024-12-04T16:30+0000",
          "height": 0.802
        },
        {
          "dt": 1733331600,
          "date": "2024-12-04T17:00+0000",
          "height": 0.882
        },
        {
          "dt": 1733333400,
          "date": "2024-12-04T17:30+0000",
          "height": 0.936
        },
        {
          "dt": 1733335200,
          "date": "2024-12-04T18:00+0000",
          "height": 0.958
        },
        {
          "dt": 1733337000,
          "date": "2024-12-04T18:30+0000",
          "height": 0.945
        },
        {
          "dt": 1733338800,
          "date": "2024-12-04T19:00+0000",
          "height": 0.893
        },
        {
          "dt": 1733340600,
          "date": "2024-12-04T19:30+0000",
          "height": 0.804
        },
        {
          "dt": 1733342400,
          "date": "2024-12-04T20:00+0000",
          "height": 0.68
        },
        {
          "dt": 1733344200,
          "date": "2024-12-04T20:30+0000",
          "height": 0.525
        },
        {
          "dt": 1733346000,
          "date": "2024-12-04T21:00+0000",
          "height": 0.345
        },
        {
          "dt": 1733347800,
          "date": "2024-12-04T21:30+0000",
          "height": 0.149
        },
        {
          "dt": 1733349600,
          "date": "2024-12-04T22:00+0000",
          "height": -0.056
        },
        {
          "dt": 1733351400,
          "date": "2024-12-04T22:30+0000",
          "height": -0.26
        },
        {
          "dt": 1733353200,
          "date": "2024-12-04T23:00+0000",
          "height": -0.455
        },
        {
          "dt": 1733355000,
          "date": "2024-12-04T23:30+0000",
          "height": -0.632
        },
        {
          "dt": 1733356800,
          "date": "2024-12-05T00:00+0000",
          "height": -0.784
        },
        {
          "dt": 1733358600,
          "date": "2024-12-05T00:30+0000",
          "height": -0.904
        },
        {
          "dt": 1733360400,
          "date": "2024-12-05T01:00+0000",
          "height": -0.99
        },
        {
          "dt": 1733362200,
          "date": "2024-12-05T01:30+0000",
          "height": -1.038
        },
        {
          "dt": 1733364000,
          "date": "2024-12-05T02:00+0000",
          "height": -1.048
        },
        {
          "dt": 1733365800,
          "date": "2024-12-05T02:30+0000",
          "height": -1.021
        },
        {
          "dt": 1733367600,
          "date": "2024-12-05T03:00+0000",
          "height": -0.96
        },
        {
          "dt": 1733369400,
          "date": "2024-12-05T03:30+0000",
          "height": -0.87
        },
        {
          "dt": 1733371200,
          "date": "2024-12-05T04:00+0000",
          "height": -0.757
        },
        {
          "dt": 1733373000,
          "date": "2024-12-05T04:30+0000",
          "height": -0.627
        },
        {
          "dt": 1733374800,
          "date": "2024-12-05T05:00+0000",
          "height": -0.489
        },
        {
          "dt": 1733376600,
          "date": "2024-12-05T05:30+0000",
          "height": -0.349
        },
        {
          "dt": 1733378400,
          "date": "2024-12-05T06:00+0000",
          "height": -0.217
        },
        {
          "dt": 1733380200,
          "date": "2024-12-05T06:30+0000",
          "height": -0.097
        },
        {
          "dt": 1733382000,
          "date": "2024-12-05T07:00+0000",
          "height": 0.004
        },
        {
          "dt": 1733383800,
          "date": "2024-12-05T07:30+0000",
          "height": 0.083
        },
        {
          "dt": 1733385600,
          "date": "2024-12-05T08:00+0000",
          "height": 0.138
        },
        {
          "dt": 1733387400,
          "date": "2024-12-05T08:30+0000",
          "height": 0.169
        },
        {
          "dt": 1733389200,
          "date": "2024-12-05T09:00+0000",
          "height": 0.179
        },
        {
          "dt": 1733391000,
          "date": "2024-12-05T09:30+0000",
          "height": 0.169
        },
        {
          "dt": 1733392800,
          "date": "2024-12-05T10:00+0000",
          "height": 0.147
        },
        {
          "dt": 1733394600,
          "date": "2024-12-05T10:30+0000",
          "height": 0.116
        },
        {
          "dt": 1733396400,
          "date": "2024-12-05T11:00+0000",
          "height": 0.083
        },
        {
          "dt": 1733398200,
          "date": "2024-12-05T11:30+0000",
          "height": 0.053
        },
        {
          "dt": 1733400000,
          "date": "2024-12-05T12:00+0000",
          "height": 0.033
        },
        {
          "dt": 1733401800,
          "date": "2024-12-05T12:30+0000",
          "height": 0.025
        },
        {
          "dt": 1733403600,
          "date": "2024-12-05T13:00+0000",
          "height": 0.035
        },
        {
          "dt": 1733405400,
          "date": "2024-12-05T13:30+0000",
          "height": 0.063
        },
        {
          "dt": 1733407200,
          "date": "2024-12-05T14:00+0000",
          "height": 0.11
        },
        {
          "dt": 1733409000,
          "date": "2024-12-05T14:30+0000",
          "height": 0.175
        }
      ]
    }
  }
]